django_er_diagram/__init__.py
django_er_diagram/constants.py
django_er_diagram/management/commands/generate_diagrams.py
django_er_diagram/settings.py
django_er_diagram/templates/erd_template.html
django_er_diagram/templates/erd_template.md
django_er_diagram/templates/index_template.html
django_er_diagram-3.4.0.dist-info/LICENSE
django_er_diagram-3.4.0.dist-info/METADATA
django_er_diagram-3.4.0.dist-info/WHEEL
django_er_diagram-3.4.0.dist-info/RECORD
