Metadata-Version: 2.1
Name: django-er-diagram
Version: 3.4.0
Summary: Auto-generate Entity-Relationship Diagrams for a Django project using Mermaid
License: MIT
Author: David Del Grosso
Author-email: daviddelgrosso97@gmail.com
Requires-Python: >=3.9
Classifier: License :: OSI Approved :: MIT License
Classifier: Programming Language :: Python :: 3
Classifier: Programming Language :: Python :: 3.9
Classifier: Programming Language :: Python :: 3.10
Classifier: Programming Language :: Python :: 3.11
Classifier: Programming Language :: Python :: 3.12
Requires-Dist: django (>=4.2)
Requires-Dist: pytest (>=7.4.4)
